odoo/addons/l10n_br_mis_report/README.rst
odoo/addons/l10n_br_mis_report/__init__.py
odoo/addons/l10n_br_mis_report/__manifest__.py
odoo/addons/l10n_br_mis_report/data/mis_report_bp.xml
odoo/addons/l10n_br_mis_report/data/mis_report_dre.xml
odoo/addons/l10n_br_mis_report/data/mis_report_styles.xml
odoo/addons/l10n_br_mis_report/i18n/l10n_br_mis_report.pot
odoo/addons/l10n_br_mis_report/i18n/pt_BR.po
odoo/addons/l10n_br_mis_report/readme/CONFIGURE.rst
odoo/addons/l10n_br_mis_report/readme/CONTRIBUTORS.rst
odoo/addons/l10n_br_mis_report/readme/DESCRIPTION.rst
odoo/addons/l10n_br_mis_report/readme/HISTORY.rst
odoo/addons/l10n_br_mis_report/readme/INSTALL.rst
odoo/addons/l10n_br_mis_report/readme/ROADMAP.rst
odoo/addons/l10n_br_mis_report/readme/USAGE.rst
odoo/addons/l10n_br_mis_report/static/description/bp.png
odoo/addons/l10n_br_mis_report/static/description/dre.png
odoo/addons/l10n_br_mis_report/static/description/icon.png
odoo/addons/l10n_br_mis_report/static/description/index.html
odoo14_addon_l10n_br_mis_report-14.0.1.0.1.dist-info/METADATA
odoo14_addon_l10n_br_mis_report-14.0.1.0.1.dist-info/WHEEL
odoo14_addon_l10n_br_mis_report-14.0.1.0.1.dist-info/top_level.txt
odoo14_addon_l10n_br_mis_report-14.0.1.0.1.dist-info/RECORD
