Metadata-Version: 2.1
Name: odoo14-addon-l10n-br-mis-report
Version: 14.0.1.0.1
Summary: Templates de relatórios contábeis brasileiros: Balanço Patrimonial e DRE
Home-page: https://github.com/OCA/l10n-brazil
Author: KMEE,Odoo Community Association (OCA)
Author-email: support@odoo-community.org
License: AGPL-3
Platform: UNKNOWN
Classifier: Programming Language :: Python
Classifier: Framework :: Odoo
Classifier: Framework :: Odoo :: 14.0
Classifier: License :: OSI Approved :: GNU Affero General Public License v3
Classifier: Development Status :: 3 - Alpha
Requires-Python: >=3.6
Requires-Dist: odoo14-addon-l10n-br-coa
Requires-Dist: odoo14-addon-mis-builder
Requires-Dist: odoo (<14.1dev,>=14.0a)
